Workbook

Sheet AS IS
A1: Tabla 1. Tiempo de ciclo por etapa (AS IS)
A2: Etapa | B2: Actividades | C2: T. ejecución (min) | D2: T. ejecución (h) | E2: T. espera (h) | F2: T. total (h) | G2: % de casos | H2: T. ponderado (h) | I2: % del total
A3: 1. Recepción y digitación | B3: Recibir documentos, digitar en el core | C3: 40 | D3: =C3/60 -> 0.66666667 | E3: 4 | F3: =D3+E3 -> 4.6666667 | G3: 1 | H3: =F3*G3 -> 4.6666667 | I3: =H3/$H$10 -> 0.059435364
A4: 2. Verificación | B4: Identidad, buró, listas de control | C4: 30 | D4: =C4/60 -> 0.5 | E4: 8 | F4: =D4+E4 -> 8.5 | G4: 1 | H4: =F4*G4 -> 8.5 | I4: =H4/$H$10 -> 0.10825727
A5: 3. Análisis de riesgo | B5: Redigitar en hoja de evaluación, evaluar | C5: 45 | D5: =C5/60 -> 0.75 | E5: 24 | F5: =D5+E5 -> 24.75 | G5: 1 | H5: =F5*G5 -> 24.75 | I5: =H5/$H$10 -> 0.3152197
A6: 4. Aprobación | B6: Resolver según nivel o comité | C6: 15 | D6: =C6/60 -> 0.25 | E6: 16 | F6: =D6+E6 -> 16.25 | G6: 1 | H6: =F6*G6 -> 16.25 | I6: =H6/$H$10 -> 0.20696243
A7: 5. Instrumentación | B7: Contrato, pagaré, garantías | C7: 45 | D7: =C7/60 -> 0.75 | E7: 12 | F7: =D7+E7 -> 12.75 | G7: 1 | H7: =F7*G7 -> 12.75 | I7: =H7/$H$10 -> 0.16238591
A8: 6. Desembolso | B8: Acreditar fondos | C8: 15 | D8: =C8/60 -> 0.25 | E8: 4 | F8: =D8+E8 -> 4.25 | G8: 1 | H8: =F8*G8 -> 4.25 | I8: =H8/$H$10 -> 0.054128635
A9: Reproceso por devolución | B9: 2.ª revisión del expediente corregido + nueva cola en fábrica | C9: 30 | D9: =C9/60 -> 0.5 | E9: =E5 -> 24 | F9: =D9+E9 -> 24.5 | G9: =C30 -> 0.3 | H9: =F9*G9 -> 7.35 | I9: =H9/$H$10 -> 0.093610698
A10: Total | H10: =SUM(H3:H9) -> 78.516667 | I10: =SUM(I3:I9) -> 1
A12: Tiempo de ciclo promedio (días hábiles de 8 h) | H12: =H10/8 -> 9.8145833
A13: Eficiencia del ciclo (ejecución ponderada / total) | H13: =SUMPRODUCT(D3:D9,G3:G9)/H10 -> 0.042241562
A14: Meta (días hábiles) | H14: 3
A15: Reducción necesaria | H15: =1-H14/H12 -> 0.69433241
A17: Tabla 2. Volumen mensual de solicitudes
A18: Concepto | B18: Detalle | C18: Solicitudes | D18: % de ingresadas
A19: Ingresadas | C19: 1500 | D19: =C19/$C$19 -> 1
A20: Llegan a análisis de riesgo | B20: 300 no llegan (incompletas o rechazadas en verificación) | C20: 1200 | D20: =C20/$C$19 -> 0.8
A21: Aprobadas | B21: 360 no aprobadas | C21: 840 | D21: =C21/$C$19 -> 0.56
A22: Desembolsadas | B22: 120 desisten después de aprobadas | C22: 720 | D22: =C22/$C$19 -> 0.48
A24: Tasa de aprobación (aprobadas / analizadas) | D24: =C21/C20 -> 0.7
A25: Devoluciones a agencia al mes | D25: =C20*C30 -> 360
A26: Casos que pasan por la fábrica (1.ª + 2.ª revisión) | D26: =C20+D25 -> 1560
A28: Tabla 3. Capacidad de la fábrica de crédito
A29: Concepto | B29: Cálculo | C29: Valor | D29: Unidad
A30: Tasa de devolución | B30: Dato del caso | C30: 0.3
A31: Analistas | B31: Dato del caso | C31: 8 | D31: personas
A32: Horas productivas por analista | B32: Dato del caso | C32: 140 | D32: h/mes
A33: Capacidad disponible | B33: Analistas × horas productivas | C33: =C31*C32 -> 1120 | D33: h/mes
A34: Demanda · primera revisión | B34: Analizadas × 45 min / 60 | C34: =C20*C5/60 -> 900 | D34: h/mes
A35: Demanda · segunda revisión | B35: Devoluciones × 30 min / 60 | C35: =D25*30/60 -> 180 | D35: h/mes
A36: Demanda total | C36: =C34+C35 -> 1080 | D36: h/mes
A37: Utilización | B37: Demanda / capacidad | C37: =C36/C33 -> 0.96428571
A38: Analistas necesarios para trabajar al 85 % | B38: Demanda / (140 × 0,85) | C38: =C36/(C32*0.85) -> 9.0756303 | D38: personas
A39: Horas que consume el reproceso | B39: Segunda revisión / demanda total | C39: =C35/C36 -> 0.16666667
A41: Tabla 4. Horas de trabajo al mes por etapa
A42: Etapa | B42: Solicitudes/mes | C42: Minutos por solicitud | D42: Horas/mes
A43: =A3 -> 1. Recepción y digitación | B43: =C19 -> 1500 | C43: =C3 -> 40 | D43: =B43*C43/60 -> 1000
A44: =A4 -> 2. Verificación | B44: =C19 -> 1500 | C44: =C4 -> 30 | D44: =B44*C44/60 -> 750
A45: =A5 -> 3. Análisis de riesgo | B45: =C20 -> 1200 | C45: =C5 -> 45 | D45: =B45*C45/60 -> 900
A46: =A6 -> 4. Aprobación | B46: =C20 -> 1200 | C46: =C6 -> 15 | D46: =B46*C46/60 -> 300
A47: =A7 -> 5. Instrumentación | B47: =C21 -> 840 | C47: =C7 -> 45 | D47: =B47*C47/60 -> 630
A48: =A8 -> 6. Desembolso | B48: =C22 -> 720 | C48: =C8 -> 15 | D48: =B48*C48/60 -> 180
A49: Reproceso (2.ª revisión) | B49: =D25 -> 360 | C49: 30 | D49: =B49*C49/60 -> 180
A50: Total | D50: =SUM(D43:D49) -> 3940
A52: Tabla 5. Causas de devolución
A53: Causa | B53: Devoluciones/mes | C53: % | D53: % acumulado
A54: Documentos de ingresos incompletos o ilegibles | B54: 144 | C54: =B54/$B$59 -> 0.4 | D54: =SUM($B$54:B54)/$B$59 -> 0.4
A55: Datos digitados que no coinciden con los documentos | B55: 108 | C55: =B55/$B$59 -> 0.3 | D55: =SUM($B$54:B55)/$B$59 -> 0.7
A56: Falta la autorización de consulta al buró | B56: 54 | C56: =B56/$B$59 -> 0.15 | D56: =SUM($B$54:B56)/$B$59 -> 0.85
A57: Dirección o referencias sin verificar | B57: 36 | C57: =B57/$B$59 -> 0.1 | D57: =SUM($B$54:B57)/$B$59 -> 0.95
A58: Otras | B58: 18 | C58: =B58/$B$59 -> 0.05 | D58: =SUM($B$54:B58)/$B$59 -> 1
A59: Total | B59: =SUM(B54:B58) -> 360 | C59: =SUM(C54:C58) -> 1
A61: Conclusiones
A62: 1. El proceso tarda 9,8 días hábiles; la meta de 3 días exige reducirlo en 69 %.
A63: 2. El 96 % del tiempo es espera. El trabajo real suma 3,3 horas por solicitud, por lo que el problema no es la velocidad de las personas sino las colas y traspasos.
A64: 3. La fábrica de crédito es el cuello de botella: trabaja al 96 % de su capacidad y el 17 % de sus horas se van en revisar otra vez expedientes devueltos.
A65: 4. Dos causas explican el 70 % de las devoluciones: documentos de ingresos y datos mal digitados. Ambas nacen en la captura en agencia.
A66: 5. Según la teoría de colas (tabla 6), la saturación de la fábrica explica solo unas 2 de las 24 horas de espera antes del análisis; el resto se debe al traslado del expediente físico y al trabajo por lotes. Contratar analistas reduciría poco el tiempo de ciclo.
A69: Tabla 6. Espera teórica en la fábrica de crédito (teoría de colas)
A70: Concepto | B70: Cálculo | C70: Valor | D70: Unidad
A71: Servidores (analistas) | B71: Tabla 3 | C71: =C31 -> 8 | D71: personas
A72: Utilización | B72: Tabla 3 | C72: =C37 -> 0.96428571
A73: Visitas a la fábrica | B73: 1.ª + 2.ª revisión | C73: =D26 -> 1560 | D73: casos/mes
A74: Tiempo medio de atención | B74: Demanda en minutos / visitas | C74: =C36*60/C73 -> 41.538462 | D74: minutos
A75: Variabilidad de las llegadas (CV²) | B75: Hoja Supuestos | C75: =Supuestos!B28 -> 1
A76: Variabilidad del tiempo de atención (CV²) | B76: Hoja Supuestos | C76: =Supuestos!B29 -> 1
A77: Espera teórica en cola | B77: Aproximación de Sakasegawa para varios servidores | C77: =((C75+C76)/2)*C72^(SQRT(2*(C71+1))-1)/(C71*(1-C72))*C74/60 -> 2.1535357 | D77: h
A78: Espera antes del análisis según el caso | B78: Tabla 1 | C78: =E5 -> 24 | D78: h
A79: Parte de la espera que explica la saturación | B79: Espera teórica / espera del caso | C79: =C77/C78 -> 0.089730653
A80: Parte que explican otras causas | B80: Traslado del expediente físico, lotes, prioridades | C80: =1-C79 -> 0.91026935

Sheet TO BE
A1: Tabla 8. Ruta de las solicitudes en el TO BE (al mes)
A2: Concepto | B2: Base (solicitudes) | C2: % aplicado | D2: Solicitudes | E2: Cómo se obtiene
A3: Solicitudes AS IS | D3: ='AS IS'!C19 -> 1500 | E3: Dato del caso
A4: Canal digital | B4: =D3 -> 1500 | C4: =Supuestos!B2 -> 0.25 | D4: =B4*C4 -> 375 | E4: Supuesto: canal digital
A5: Canal físico (agencia) | B5: =D3 -> 1500 | C5: =1-C4 -> 0.75 | D5: =B5*C5 -> 1125 | E5: Resto de solicitudes
A6: No llegan a decisión | B6: =D3 -> 1500 | C6: =1-'AS IS'!D20 -> 0.2 | D6: =B6*C6 -> 300 | E6: Igual que el AS IS
A7: Llegan a decisión | B7: =D3 -> 1500 | C7: =1-C6 -> 0.8 | D7: =B7*C7 -> 1200 | E7: Igual que el AS IS
A8: Aprobadas | B8: =D7 -> 1200 | C8: ='AS IS'!D24 -> 0.7 | D8: =B8*C8 -> 840 | E8: Igual tasa de aprobación que el AS IS
A9: Rechazadas | B9: =D7 -> 1200 | C9: =1-C8 -> 0.3 | D9: =B9*C9 -> 360 | E9: Resto
A10: N1 · Aprobación directa por el sistema | B10: =D8 -> 840 | C10: =Supuestos!B3 -> 0.33333333 | D10: =B10*C10 -> 280 | E10: Supuesto: buró A, ingreso verificado en fuente, cuota ≤ 40 %
A11: N0 · Rechazo automático | B11: =D9 -> 360 | C11: =Supuestos!B4 -> 0.33333333 | D11: =B11*C11 -> 120 | E11: Supuesto: incumple reglas de política
A12: Revisión humana (N2 a N4) | B12: =D7 -> 1200 | C12: =D12/B12 -> 0.66666667 | D12: =D7-D10-D11 -> 800 | E12: Las que el sistema no resuelve
A13: N2 · Revisión parcial (solo ingresos) | B13: =D12 -> 800 | C13: =Supuestos!B5 -> 0.4 | D13: =B13*C13 -> 320 | E13: Supuesto
A14: N3 · Revisión completa | B14: =D12 -> 800 | C14: =Supuestos!B6 -> 0.45 | D14: =B14*C14 -> 360 | E14: Supuesto
A15: N4 · Comité | B15: =D12 -> 800 | C15: =Supuestos!B7 -> 0.15 | D15: =B15*C15 -> 120 | E15: Supuesto
A16: Aprobadas por revisión humana | B16: =D8 -> 840 | C16: =D16/B16 -> 0.66666667 | D16: =D8-D10 -> 560 | E16: Aprobadas que no fueron directas
A18: Tabla 9. Tiempos de diseño por canal
A19: Etapa | B19: Qué cambia | C19: Agencia: ejecución (min) | D19: Agencia: espera (h) | E19: Digital: ejecución (min) | F19: Digital: espera (h)
A20: Captura y precalificación | B20: Una sola captura en plataforma; autorizaciones firmadas y escaneadas | C20: 25 | D20: 4 | E20: 0 | F20: 0
A21: Validación documental | B21: Software lee documentos; buró, listas, Registro Civil y SRI en paralelo | C21: 5 | D21: 0.5 | E21: 0 | F21: 0.5
A22: Instrumentación | B22: Documentos generados por el sistema | C22: 20 | D22: 2 | E22: 20 | F22: 4
A23: Instrumentación con aprobación directa | B23: Firma en la misma visita, o impresa y escaneada | C23: 20 | D23: 0.5 | E23: 20 | F23: 2
A24: Desembolso | B24: Acreditación integrada al core | C24: 5 | D24: 1 | E24: 5 | F24: 1
A26: Tabla 10. Tiempos de diseño por nivel de revisión
A27: Nivel | B27: Qué revisa | C27: Analista (min) | D27: Espera antes del analista (h) | E27: Aprobación (min) | F27: Espera de aprobación (h)
A28: N2 · Revisión parcial | B28: Solo ingresos | C28: 15 | D28: 2 | E28: 10 | F28: 2
A29: N3 · Revisión completa | B29: Todo el expediente | C29: 30 | D29: 2 | E29: 10 | F29: 4
A30: N4 · Comité | B30: Todo el expediente + comité | C30: 30 | D30: 2 | E30: 25 | F30: 8
A32: Tabla 11. Tiempo por etapa · caso típico (revisión completa, en agencia)
A33: Etapa | B33: Actividades | C33: T. ejecución (min) | D33: T. ejecución (h) | E33: T. espera (h) | F33: T. total (h) | G33: % de casos | H33: T. ponderado (h) | I33: % del total
A34: 1. Captura y precalificación | B34: =B20 -> Una sola captura en plataforma; autorizaciones firmadas y escaneadas | C34: =C20 -> 25 | D34: =C34/60 -> 0.41666667 | E34: =D20 -> 4 | F34: =D34+E34 -> 4.4166667 | G34: 1 | H34: =F34*G34 -> 4.4166667 | I34: =H34/$H$41 -> 0.28900804
A35: 2. Validación documental | B35: =B21 -> Software lee documentos; buró, listas, Registro Civil y SRI en paralelo | C35: =C21 -> 5 | D35: =C35/60 -> 0.083333333 | E35: =D21 -> 0.5 | F35: =D35+E35 -> 0.58333333 | G35: 1 | H35: =F35*G35 -> 0.58333333 | I35: =H35/$H$41 -> 0.038170874
A36: 3. Revisión del analista | B36: =B29 -> Todo el expediente | C36: =C29 -> 30 | D36: =C36/60 -> 0.5 | E36: =D29 -> 2 | F36: =D36+E36 -> 2.5 | G36: 1 | H36: =F36*G36 -> 2.5 | I36: =H36/$H$41 -> 0.16358946
A37: Reproceso por devolución | B37: 2.ª revisión del expediente corregido + espera antes del analista | C37: 30 | D37: =C37/60 -> 0.5 | E37: =D29 -> 2 | F37: =D37+E37 -> 2.5 | G37: =D82 -> 0.07953 | H37: =F37*G37 -> 0.198825 | I37: =H37/$H$41 -> 0.01301027
A38: 4. Aprobación | B38: =B29 -> Todo el expediente | C38: =E29 -> 10 | D38: =C38/60 -> 0.16666667 | E38: =F29 -> 4 | F38: =D38+E38 -> 4.1666667 | G38: 1 | H38: =F38*G38 -> 4.1666667 | I38: =H38/$H$41 -> 0.2726491
A39: 5. Instrumentación | B39: =B22 -> Documentos generados por el sistema | C39: =C22 -> 20 | D39: =C39/60 -> 0.33333333 | E39: =D22 -> 2 | F39: =D39+E39 -> 2.3333333 | G39: 1 | H39: =F39*G39 -> 2.3333333 | I39: =H39/$H$41 -> 0.15268349
A40: 6. Desembolso | B40: =B24 -> Acreditación integrada al core | C40: =C24 -> 5 | D40: =C40/60 -> 0.083333333 | E40: =D24 -> 1 | F40: =D40+E40 -> 1.0833333 | G40: 1 | H40: =F40*G40 -> 1.0833333 | I40: =H40/$H$41 -> 0.070888765
A41: Total | H41: =SUM(H34:H40) -> 15.282158 | I41: =SUM(I34:I40) -> 1
A43: Tiempo de ciclo (días hábiles de 8 h) | H43: =H41/8 -> 1.9102698
A45: Tabla 12. Tiempo por tipo de solicitud aprobada
A46: Tipo | B46: Canal | C46: Captura (h) | D46: Validación (h) | E46: Revisión (h) | F46: Aprobación (h) | G46: Reproceso (h) | H46: Instrumentación (h) | I46: Desembolso (h) | J46: Total (h) | K46: Días hábiles | L46: Aprobadas/mes
A47: N1 · Aprobación directa | B47: Agencia | C47: =D20+C20/60 -> 4.4166667 | D47: =D21+C21/60 -> 0.58333333 | E47: 0 | F47: 0 | G47: 0 | H47: =D23+C23/60 -> 0.83333333 | I47: =D24+C24/60 -> 1.0833333 | J47: =SUM(C47:I47) -> 6.9166667 | K47: =J47/8 -> 0.86458333 | L47: =D10*$C$5 -> 210
A48: N1 · Aprobación directa | B48: Digital | C48: =F20+E20/60 -> 0 | D48: =F21+E21/60 -> 0.5 | E48: 0 | F48: 0 | G48: 0 | H48: =F23+E23/60 -> 2.3333333 | I48: =F24+E24/60 -> 1.0833333 | J48: =SUM(C48:I48) -> 3.9166667 | K48: =J48/8 -> 0.48958333 | L48: =D10*$C$4 -> 70
A49: N2 · Revisión parcial | B49: Agencia | C49: =D20+C20/60 -> 4.4166667 | D49: =D21+C21/60 -> 0.58333333 | E49: =D28+C28/60 -> 2.25 | F49: =F28+E28/60 -> 2.1666667 | G49: =$H$37 -> 0.198825 | H49: =D22+C22/60 -> 2.3333333 | I49: =D24+C24/60 -> 1.0833333 | J49: =SUM(C49:I49) -> 13.032158 | K49: =J49/8 -> 1.6290198 | L49: =D16*Supuestos!B5*$C$5 -> 168
A50: N2 · Revisión parcial | B50: Digital | C50: =F20+E20/60 -> 0 | D50: =F21+E21/60 -> 0.5 | E50: =D28+C28/60 -> 2.25 | F50: =F28+E28/60 -> 2.1666667 | G50: =$H$37 -> 0.198825 | H50: =F22+E22/60 -> 4.3333333 | I50: =F24+E24/60 -> 1.0833333 | J50: =SUM(C50:I50) -> 10.532158 | K50: =J50/8 -> 1.3165198 | L50: =D16*Supuestos!B5*$C$4 -> 56
A51: N3 · Revisión completa | B51: Agencia | C51: =D20+C20/60 -> 4.4166667 | D51: =D21+C21/60 -> 0.58333333 | E51: =D29+C29/60 -> 2.5 | F51: =F29+E29/60 -> 4.1666667 | G51: =$H$37 -> 0.198825 | H51: =D22+C22/60 -> 2.3333333 | I51: =D24+C24/60 -> 1.0833333 | J51: =SUM(C51:I51) -> 15.282158 | K51: =J51/8 -> 1.9102698 | L51: =D16*Supuestos!B6*$C$5 -> 189
A52: N3 · Revisión completa | B52: Digital | C52: =F20+E20/60 -> 0 | D52: =F21+E21/60 -> 0.5 | E52: =D29+C29/60 -> 2.5 | F52: =F29+E29/60 -> 4.1666667 | G52: =$H$37 -> 0.198825 | H52: =F22+E22/60 -> 4.3333333 | I52: =F24+E24/60 -> 1.0833333 | J52: =SUM(C52:I52) -> 12.782158 | K52: =J52/8 -> 1.5977698 | L52: =D16*Supuestos!B6*$C$4 -> 63
A53: N4 · Comité | B53: Agencia | C53: =D20+C20/60 -> 4.4166667 | D53: =D21+C21/60 -> 0.58333333 | E53: =D30+C30/60 -> 2.5 | F53: =F30+E30/60 -> 8.4166667 | G53: =$H$37 -> 0.198825 | H53: =D22+C22/60 -> 2.3333333 | I53: =D24+C24/60 -> 1.0833333 | J53: =SUM(C53:I53) -> 19.532158 | K53: =J53/8 -> 2.4415198 | L53: =D16*Supuestos!B7*$C$5 -> 63
A54: N4 · Comité | B54: Digital | C54: =F20+E20/60 -> 0 | D54: =F21+E21/60 -> 0.5 | E54: =D30+C30/60 -> 2.5 | F54: =F30+E30/60 -> 8.4166667 | G54: =$H$37 -> 0.198825 | H54: =F22+E22/60 -> 4.3333333 | I54: =F24+E24/60 -> 1.0833333 | J54: =SUM(C54:I54) -> 17.032158 | K54: =J54/8 -> 2.1290198 | L54: =D16*Supuestos!B7*$C$4 -> 21
A55: Total | L55: =SUM(L47:L54) -> 840
A57: Promedio ponderado (días) | K57: =SUMPRODUCT(K47:K54,L47:L54)/L55 -> 1.4564993
A58: Caso más lento (días) | K58: =MAX(K47:K54) -> 2.4415198
A59: Aprobados en 1 día o menos | K59: =SUMIF(K47:K54,"<=1",L47:L54)/L55 -> 0.33333333
A61: Tabla 13. Capacidad de la fábrica de crédito (TO BE)
A62: Concepto | B62: Casos/mes | C62: Minutos por caso | D62: Horas/mes
A63: Revisión parcial (N2) | B63: =D13 -> 320 | C63: =C28 -> 15 | D63: =B63*C63/60 -> 80
A64: Revisión completa (N3) | B64: =D14 -> 360 | C64: =C29 -> 30 | D64: =B64*C64/60 -> 180
A65: Revisión para comité (N4) | B65: =D15 -> 120 | C65: =C30 -> 30 | D65: =B65*C65/60 -> 60
A66: Segundas revisiones (revisión humana × tasa de devolución) | B66: =D12*D82 -> 63.624 | C66: 30 | D66: =B66*C66/60 -> 31.812
A67: Documentos que el software no lee con confianza | B67: =D3*Supuestos!B8 -> 225 | C67: =Supuestos!B9 -> 5 | D67: =B67*C67/60 -> 18.75
A68: Demanda total | D68: =SUM(D63:D67) -> 370.562
A70: Capacidad disponible (igual que el AS IS, h/mes) | D70: ='AS IS'!C33 -> 1120
A71: Utilización (demanda / capacidad) | D71: =D68/D70 -> 0.33085893
A72: Analistas necesarios para trabajar al 85 % | D72: =D68/('AS IS'!C32*0.85) -> 3.1139664
A74: Tabla 14. Devoluciones esperadas en el TO BE
A75: Causa | B75: AS IS | C75: Reducción | D75: TO BE | E75: Cómo se logra
A76: ='AS IS'!A54 -> Documentos de ingresos incompletos o ilegibles | B76: ='AS IS'!B54 -> 144 | C76: =Supuestos!C24 -> 0.681 | D76: =B76*(1-C76) -> 45.936 | E76: Verificación en fuente según el tipo de ingreso
A77: ='AS IS'!A55 -> Datos digitados que no coinciden con los documentos | B77: ='AS IS'!B55 -> 108 | C77: =Supuestos!B10 -> 0.9 | D77: =B77*(1-C77) -> 10.8 | E77: El software extrae el dato una sola vez
A78: ='AS IS'!A56 -> Falta la autorización de consulta al buró | B78: ='AS IS'!B56 -> 54 | C78: =Supuestos!B11 -> 0.95 | D78: =B78*(1-C78) -> 2.7 | E78: No se puede precalificar sin la autorización firmada
A79: ='AS IS'!A57 -> Dirección o referencias sin verificar | B79: ='AS IS'!B57 -> 36 | C79: =Supuestos!B12 -> 0.5 | D79: =B79*(1-C79) -> 18 | E79: Regla de documentos requeridos por perfil
A80: ='AS IS'!A58 -> Otras | B80: ='AS IS'!B58 -> 18 | C80: 0 | D80: =B80*(1-C80) -> 18 | E80: Sin control definido
A81: Total | B81: =SUM(B76:B80) -> 360 | C81: =1-D81/B81 -> 0.7349 | D81: =SUM(D76:D80) -> 95.436
A82: Tasa de devolución TO BE (devoluciones / llegan a decisión) | D82: =D81/D7 -> 0.07953
A84: Tabla 15. Horas de trabajo al mes (TO BE)
A85: Etapa | B85: Solicitudes/mes | C85: Minutos por solicitud | D85: Horas/mes
A86: Captura en agencia | B86: =D5 -> 1125 | C86: =C20 -> 25 | D86: =B86*C86/60 -> 468.75
A87: Validación en agencia | B87: =D5 -> 1125 | C87: =C21 -> 5 | D87: =B87*C87/60 -> 93.75
A88: Fábrica de crédito (tabla 13) | D88: =D68 -> 370.562
A89: Aprobación (N2 y N3: 10 min; N4: 25 min) | B89: =D12 -> 800 | D89: =(D13*E28+D14*E29+D15*E30)/60 -> 163.33333
A90: Instrumentación | B90: ='AS IS'!C21 -> 840 | C90: =C22 -> 20 | D90: =B90*C90/60 -> 280
A91: Desembolso | B91: ='AS IS'!C22 -> 720 | C91: =C24 -> 5 | D91: =B91*C91/60 -> 60
A92: Total | D92: =SUM(D86:D91) -> 1436.3953
A94: Tabla 16. Comparación AS IS – TO BE
A95: Indicador | B95: AS IS | C95: TO BE | D95: Diferencia | E95: Variación
A96: Tiempo de ciclo promedio (días) | B96: ='AS IS'!H12 -> 9.8145833 | C96: =K57 -> 1.4564993 | D96: =C96-B96 -> -8.358084 | E96: =(C96-B96)/B96 -> -0.85159846
A97: Caso más lento (días) | B97: =SUM('AS IS'!F3:F9)/8 -> 11.958333 | C97: =K58 -> 2.4415198 | D97: =C97-B97 -> -9.5168135 | E97: =(C97-B97)/B97 -> -0.7958311
A98: Devoluciones al mes | B98: ='AS IS'!D25 -> 360 | C98: =D81 -> 95.436 | D98: =C98-B98 -> -264.564 | E98: =(C98-B98)/B98 -> -0.7349
A99: Utilización de la fábrica | B99: ='AS IS'!C37 -> 0.96428571 | C99: =D71 -> 0.33085893 | D99: =C99-B99 -> -0.63342679 | E99: =(C99-B99)/B99 -> -0.65688704
A100: Analistas necesarios al 85 % | B100: ='AS IS'!C38 -> 9.0756303 | C100: =D72 -> 3.1139664 | D100: =C100-B100 -> -5.9616639 | E100: =(C100-B100)/B100 -> -0.65688704
A101: Horas de trabajo al mes | B101: ='AS IS'!D50 -> 3940 | C101: =D92 -> 1436.3953 | D101: =C101-B101 -> -2503.6047 | E101: =(C101-B101)/B101 -> -0.63543266
A103: Tabla 17. Tiempo por etapa: AS IS frente a TO BE caso típico (horas)
A104: Etapa | B104: AS IS | C104: TO BE
A105: 1. Recepción / captura | B105: ='AS IS'!H3 -> 4.6666667 | C105: =H34 -> 4.4166667
A106: 2. Verificación / validación | B106: ='AS IS'!H4 -> 8.5 | C106: =H35 -> 0.58333333
A107: 3. Análisis / revisión | B107: ='AS IS'!H5 -> 24.75 | C107: =H36 -> 2.5
A108: Reproceso | B108: ='AS IS'!H9 -> 7.35 | C108: =H37 -> 0.198825
A109: 4. Aprobación | B109: ='AS IS'!H6 -> 16.25 | C109: =H38 -> 4.1666667
A110: 5. Instrumentación | B110: ='AS IS'!H7 -> 12.75 | C110: =H39 -> 2.3333333
A111: 6. Desembolso | B111: ='AS IS'!H8 -> 4.25 | C111: =H40 -> 1.0833333
A112: Total | B112: =SUM(B105:B111) -> 78.516667 | C112: =SUM(C105:C111) -> 15.282158
...

Sheet Matriz_Automatizables
A1: Actividad AS-IS | B1: Etapa | C1: Volumen | D1: Repetitividad | E1: Basada en reglas | F1: Datos digitales | G1: Riesgo de error humano | H1: Potencial | I1: Clase | J1: Decisión | K1: Habilitador | L1: Justificación por el diagnóstico
A2: Pesos (editables) | C2: 0.2 | D2: 0.2 | E2: 0.2 | F2: 0.2 | G2: 0.2 | H2: =SUM(C2:G2) -> 1
A3: 1.1 Recibir documentos físicos | B3: 1 | C3: 5 | D3: 5 | E3: 4 | F3: 1 | G3: 4 | H3: =SUMPRODUCT(C3:G3,$C$5:$G$5) -> 90 | I3: =IF(H3>=4,"Alto",IF(H3>=3,"Medio","Bajo")) -> Alto | J3: Digitalizar | K3: Plataforma con canal digital y asistido; DMN de requisitos por perfil | L3: 144 devoluciones por documentos de ingreso
A4: 1.2 Digitar solicitud en el core | B4: 1 | C4: 5 | D4: 5 | E4: 5 | F4: 2 | G4: 5 | H4: =SUMPRODUCT(C4:G4,$C$5:$G$5) -> 103 | I4: =IF(H4>=4,"Alto",IF(H4>=3,"Medio","Bajo")) -> Alto | J4: Automatizar | K4: Software de extracción: el dato se lee una vez del documento | L4: 108 devoluciones por datos que no coinciden
A5: 2.1 Validar identidad y consultar buró | B5: 2 | C5: 5 | D5: 5 | E5: 5 | F5: 4 | G5: 4 | H5: =SUMPRODUCT(C5:G5,$C$5:$G$5) -> 107 | I5: =IF(H5>=4,"Alto",IF(H5>=3,"Medio","Bajo")) -> Alto | J5: Automatizar | K5: Biometría del Registro Civil y buró por integración | L5: 54 devoluciones por autorización; quien origina verifica
A6: 2.2 Revisar listas de control | B6: 2 | C6: 5 | D6: 5 | E6: 5 | F6: 4 | G6: 5 | H6: =SUMPRODUCT(C6:G6,$C$5:$G$5) -> 111 | I6: =IF(H6>=4,"Alto",IF(H6>=3,"Medio","Bajo")) -> Alto | J6: Automatizar | K6: Consulta automática con evidencia y alerta a Cumplimiento | L6: Revisión sin evidencia [p.1]
A7: 2.3 Enviar expediente físico a fábrica | B7: 2 | C7: 5 | D7: 5 | E7: 5 | F7: 1 | G7: 3 | H7: =SUMPRODUCT(C7:G7,$C$5:$G$5) -> 91 | I7: =IF(H7>=4,"Alto",IF(H7>=3,"Medio","Bajo")) -> Alto | J7: Eliminar | K7: Expediente digital en la plataforma | L7: Espera de 24 h previa a análisis
A8: 3.1 Redigitar datos en hoja de evaluación | B8: 3 | C8: 5 | D8: 5 | E8: 5 | F8: 3 | G8: 5 | H8: =SUMPRODUCT(C8:G8,$C$5:$G$5) -> 107 | I8: =IF(H8>=4,"Alto",IF(H8>=3,"Medio","Bajo")) -> Alto | J8: Eliminar | K8: El analista trabaja sobre el dato extraído | L8: Doble digitación; fábrica al 96,4 %
A9: 3.2 Evaluar riesgo crediticio | B9: 3 | C9: 5 | D9: 4 | E9: 3 | F9: 3 | G9: 3 | H9: =SUMPRODUCT(C9:G9,$C$5:$G$5) -> 84 | I9: =IF(H9>=4,"Alto",IF(H9>=3,"Medio","Bajo")) -> Alto | J9: Asistir (no sustituir) | K9: DMN de decisión con carriles; el analista resuelve la zona gris | L9: Restricción del proceso
A10: 3.3 Completar o corregir expediente | B10: 3 | C10: 3 | D10: 3 | E10: 2 | F10: 2 | G10: 3 | H10: =SUMPRODUCT(C10:G10,$C$5:$G$5) -> 60 | I10: =IF(H10>=4,"Alto",IF(H10>=3,"Medio","Bajo")) -> Alto | J10: Prevenir | K10: La corrección ocurre en la captura, guiada por la plataforma | L10: 30 % de devolución
A11: 3.4 Revisar expediente corregido | B11: 3 | C11: 3 | D11: 4 | E11: 3 | F11: 3 | G11: 3 | H11: =SUMPRODUCT(C11:G11,$C$5:$G$5) -> 74 | I11: =IF(H11>=4,"Alto",IF(H11>=3,"Medio","Bajo")) -> Alto | J11: Prevenir | K11: Se reduce al bajar la devolución residual | L11: 360 revisiones/mes
A12: 4.1 Aprobar excepción por correo | B12: 4 | C12: 2 | D12: 2 | E12: 2 | F12: 1 | G12: 5 | H12: =SUMPRODUCT(C12:G12,$C$5:$G$5) -> 54 | I12: =IF(H12>=4,"Alto",IF(H12>=3,"Medio","Bajo")) -> Alto | J12: Digitalizar registro | K12: Flujo electrónico con registro; la decisión sigue siendo humana | L12: Excepciones sin registro [p.1]
A13: 4.2 Resolver solicitud según nivel | B13: 4 | C13: 5 | D13: 4 | E13: 4 | F13: 3 | G13: 3 | H13: =SUMPRODUCT(C13:G13,$C$5:$G$5) -> 89 | I13: =IF(H13>=4,"Alto",IF(H13>=3,"Medio","Bajo")) -> Alto | J13: Automatizar flujo | K13: Atribuciones electrónicas; aprobación automática por DMN bajo umbral | L13: Espera de 16 h por comité
A14: 5.1 Elaborar contrato, pagaré y garantías | B14: 5 | C14: 4 | D14: 5 | E14: 5 | F14: 3 | G14: 4 | H14: =SUMPRODUCT(C14:G14,$C$5:$G$5) -> 98 | I14: =IF(H14>=4,"Alto",IF(H14>=3,"Medio","Bajo")) -> Alto | J14: Automatizar | K14: Generación automática de documentos | L14: Espera de 12 h y 45 min de trabajo
A15: 6.1 Acreditar fondos en el core | B15: 6 | C15: 4 | D15: 5 | E15: 5 | F15: 4 | G15: 4 | H15: =SUMPRODUCT(C15:G15,$C$5:$G$5) -> 102 | I15: =IF(H15>=4,"Alto",IF(H15>=3,"Medio","Bajo")) -> Alto | J15: Automatizar | K15: Desembolso integrado tras checklist | L15: 15 min y espera de 4 h

Sheet Supuestos
A1: Supuesto | B1: Valor | D1: Fuente
A2: Solicitudes que llegan por canal digital | B2: 0.25 | D2: INEC TIC 2024: 77 % usa internet y 58 % tiene smartphone; Findex 2025: 43 % hace pagos digitales
A3: Aprobaciones que resuelve el sistema sin analista (N1) | B3: =1/3 -> 0.33333333 | D3: Cornerstone Advisors 2022: 1 de cada 3 préstamos en entidades con decisión automática
A4: Rechazos automáticos (N0) | B4: =1/3 -> 0.33333333 | D4: Mismo criterio que N1
A5: Revisión humana que va a N2 | B5: 0.4 | D5: Criterio de diseño
A6: Revisión humana que va a N3 | B6: 0.45 | D6: Criterio de diseño
A7: Revisión humana que va a N4 | B7: =1-B5-B6 -> 0.15 | D7: Resto
A8: Documentos que el software no lee con confianza | B8: 0.15 | D8: Criterio conservador
A9: Minutos para revisar a mano esos documentos | B9: 5 | D9: Criterio de diseño
A10: Reducción de devoluciones por datos mal digitados | B10: 0.9 | D10: El dato se extrae una sola vez del documento
A11: Reducción de devoluciones por falta de autorización de buró | B11: 0.95 | D11: La precalificación no avanza sin la autorización firmada
A12: Reducción de devoluciones por dirección o referencias | B12: 0.5 | D12: Efecto parcial de la regla de documentos requeridos
A13: Corrección en agencia (AS IS) | B13: 0 | D13: El caso no da el dato; se toma 0 h (el expediente vuelve a la cola de fábrica)
A14: Capacidad de pago máxima | B14: 0.4 | D14: Política de la entidad
A16: Tipo de ingreso del solicitante | B16: % de solicitantes | C16: Reducción de devoluciones por ingresos | D16: Fuente
A17: Dependiente afiliado al IESS | B17: 0.45 | C17: 0.75 | D17: IESS / INEC 2026: 45,4 % de la PEA cotiza
A18: Remesista que recibe en el banco | B18: 0.065 | C18: 1 | D18: Findex 2025: 13 % de adultos recibe remesas (se asume la mitad en el banco)
A19: Remesista que recibe por otra vía | B19: 0.065 | C19: 0.5 | D19: Idem
A20: Independiente con factura electrónica | B20: 0.08 | C20: 0.95 | D20: SRI: catastro RIMPE, emprendedores frente a negocios populares
A21: Independiente sin factura (negocio popular u otros) | B21: 0.34 | C21: 0.5 | D21: Resto
A22: Total | B22: =SUM(B17:B21) -> 1
A24: Reducción ponderada de devoluciones por ingresos | C24: =SUMPRODUCT(B17:B21,C17:C21) -> 0.681
A27: Supuesto para teoría de colas | B27: Valor | D27: Fuente
A28: Variabilidad de las llegadas (CV²) | B28: 1 | D28: Llegadas aleatorias (proceso de Poisson); el caso no da la dispersión
A29: Variabilidad del tiempo de atención (CV²) | B29: 1 | D29: Tiempos exponenciales; el caso solo da promedios
